MANIFEST.in
example.py
setup.py
etiquetando/__init__.py
etiquetando/cache.py
etiquetando.egg-info/PKG-INFO
etiquetando.egg-info/SOURCES.txt
etiquetando.egg-info/dependency_links.txt
etiquetando.egg-info/not-zip-safe
etiquetando.egg-info/requires.txt
etiquetando.egg-info/top_level.txt
etiquetando/data/stop_ptbr.txt
etiquetando/data/tags_ptbr.txt