Metadata-Version: 1.0
Name: etiquetando
Version: 0.1
Summary: Term extractor (tags) for Brazilian Portuguese (pt-br)
Home-page: http://github.com/TracyWebTech/etiquetando
Author: Sergio Oliveira
Author-email: sergio@tracy.com.br
License: BSD
Platform: UNKNOWN
Classifier: Development Status :: 4 - Beta
Classifier: Intended Audience :: Developers
Classifier: License :: OSI Approved :: BSD License
Classifier: Operating System :: OS Independent
Classifier: Programming Language :: Python
Classifier: Programming Language :: Python :: 2.6
Classifier: Programming Language :: Python :: 2.7
Classifier: Natural Language :: Portuguese (Brazilian)
